utils/__init__.py
utils/aws_dynamodb_utils.py
utils/aws_s3_utils.py
utils/aws_secrets_utils.py
utils/aws_sns_utils.py
utils/aws_sqs_utils.py
utils/aws_step_functions_utils.py
utils/contants.py
utils/hashing_utils.py
utils/jwt_utils.py
genflowly_lambda_utils-0.0.11.dist-info/METADATA
genflowly_lambda_utils-0.0.11.dist-info/WHEEL
genflowly_lambda_utils-0.0.11.dist-info/top_level.txt
genflowly_lambda_utils-0.0.11.dist-info/RECORD
